kyoslib_py/__init__.py
kyoslib_py/forward_curve.py
kyoslib_py/front_end.py
kyoslib_py/historical_price.py
kyoslib_py/kyos_api.py
kyoslib_py/kyos_utils.py
kyoslib_py/settings.py
kyoslib_py/simulation.py
kyoslib_py/tradable_product.py
kyoslib_py/valuation_interface.py
kyoslib_py-5.4.5.dist-info/LICENSE.txt
kyoslib_py-5.4.5.dist-info/METADATA
kyoslib_py-5.4.5.dist-info/WHEEL
kyoslib_py-5.4.5.dist-info/entry_points.txt
kyoslib_py-5.4.5.dist-info/RECORD
