Metadata-Version: 2.1
Name: kyoslib_py
Version: 5.4.5
Summary: KYOS shared lib code as python package
Home-page: http://github.com/kyosenergy/kyoslib_py
License: MIT
Author: KYOS
Author-email: support@kyos.com
Requires-Python: >=3.11,<3.14
Classifier: License :: OSI Approved :: MIT License
Classifier: Programming Language :: Python :: 3
Classifier: Programming Language :: Python :: 3.11
Requires-Dist: h5py (>=3.9.0,<4.0.0)
Requires-Dist: mkdocstrings-python (>=1.7,<3.0)
Requires-Dist: numba (>=0.57.1,<0.64.0)
Requires-Dist: numpy (>=1.24.4,<3.0.0)
Requires-Dist: pandas (>=2.0.0,<3.0.0)
Requires-Dist: plotly (>=5.16.1,<7.0.0)
Requires-Dist: postmarker (>=1.0,<2.0)
Requires-Dist: requests (>=2.31.0,<3.0.0)
Project-URL: Documentation, https://kyosenergy.github.io/kyoslib_py/
Project-URL: Repository, http://github.com/kyosenergy/kyoslib_py
